digatron_utility/__init__.py
digatron_utility/read.py
digatron_utility-0.0.0.dist-info/LICENSE.txt
digatron_utility-0.0.0.dist-info/METADATA
digatron_utility-0.0.0.dist-info/WHEEL
digatron_utility-0.0.0.dist-info/top_level.txt
digatron_utility-0.0.0.dist-info/RECORD
