Metadata-Version: 2.1
Name: digatron-utility
Version: 0.0.0
Summary: Utility tools for processing Digatron battery tester data
Home-page: https://github.com/OpenBattTools/digatron-utility
Author: Lukas Gold
Author-email: lukas.gold@isc.fraunhofer.de
License: AGPL-3.0-or-later
Project-URL: Documentation, https://github.com/OpenBattTools/digatron-utility
Project-URL: Source, https://github.com/OpenBattTools/digatron-utility
Platform: any
Classifier: Development Status :: 3 - Alpha
Classifier: Programming Language :: Python
Requires-Python: >=3.8
License-File: LICENSE.txt
Requires-Dist: batt-utility
Requires-Dist: numpy
Requires-Dist: pandas
Requires-Dist: pathlib
Requires-Dist: pydantic
Requires-Dist: scipy
Requires-Dist: typing-extensions
Requires-Dist: strenum ; python_version < "3.11"
Provides-Extra: testing
Requires-Dist: setuptools ; extra == 'testing'
Requires-Dist: pytest ; extra == 'testing'
Requires-Dist: pytest-cov ; extra == 'testing'
